mixon/__init__.py
mixon-0.0.3.dist-info/LICENSE
mixon-0.0.3.dist-info/METADATA
mixon-0.0.3.dist-info/WHEEL
mixon-0.0.3.dist-info/top_level.txt
mixon-0.0.3.dist-info/RECORD
