Metadata-Version: 2.1
Name: mixon
Version: 0.0.3
Summary: A variant of json which is convenient for long raw txt fields.
Home-page: https://github.com/claydodo/mixon
Author: claydodo
Author-email: claydodo@foxmail.com
License: UNKNOWN
Project-URL: Bug Tracker, https://github.com/claydodo/mixon/issues
Platform: UNKNOWN
Classifier: Programming Language :: Python :: 3
Classifier: License :: OSI Approved :: The Unlicense (Unlicense)
Classifier: Operating System :: OS Independent
Requires-Python: >=3.0
License-File: LICENSE
